graphgrid_provider/__init__.py
graphgrid_provider/operators/__init__.py
graphgrid_provider/operators/graphgrid_docker.py
airflow_provider_graphgrid-2.0.3.dist-info/METADATA
airflow_provider_graphgrid-2.0.3.dist-info/WHEEL
airflow_provider_graphgrid-2.0.3.dist-info/entry_points.txt
airflow_provider_graphgrid-2.0.3.dist-info/top_level.txt
airflow_provider_graphgrid-2.0.3.dist-info/RECORD
