Metadata-Version: 2.1
Name: airflow-provider-graphgrid
Version: 2.0.3
Summary: GraphGrid Provider Package
Home-page: https://docs.graphgrid.com/2.0/#/
Author: graphgrid
Author-email: 
License: Apache License 2.0
Classifier: Development Status :: 5 - Production/Stable
Classifier: Programming Language :: Python :: 3.6
Classifier: Programming Language :: Python :: 3.7
Classifier: Programming Language :: Python :: 3.8
Requires-Python: !=3.9.*, >=3.6
Requires-Dist: apache-airflow (>=2.2.2)
Requires-Dist: apache-airflow-providers-docker (>=2.3.0)
